fastrtc_kroko/__init__.py
fastrtc_kroko/model.py
fastrtc_kroko/test_file.wav
fastrtc_kroko-0.1.2.dist-info/METADATA
fastrtc_kroko-0.1.2.dist-info/WHEEL
fastrtc_kroko-0.1.2.dist-info/licenses/LICENCE
fastrtc_kroko-0.1.2.dist-info/RECORD
