Metadata-Version: 2.4
Name: fastrtc-kroko
Version: 0.1.2
Summary: The realtime communication library for Python. With support for Kroko-ASR model.
Project-URL: repository, https://github.com/sgarg26/fastrtc-kroko
Project-URL: issues, https://github.com/sgarg26/fastrtc-kroko/issues
Author-email: Siddharth Garg <YOUREMAIL@domain.com>
License-Expression: MIT
License-File: LICENCE
Keywords: audio,audio processing,computer vision,gradio-custom-component,image,machine learning,realtime,streaming,video,video processing,webrtc
Requires-Python: >=3.10
Requires-Dist: click
Requires-Dist: fastrtc[stt,vad]
Requires-Dist: librosa
Requires-Dist: numpy>=2.0.2
Requires-Dist: python-dotenv
Requires-Dist: sherpa-onnx
Requires-Dist: torch
